<?xml version="1.0" encoding="UTF-8"?>
<file
  name="app/Http/Middleware/Authenticate.php"
  last-modified="1474359102000"
  file="/var/jenkins_home/workspace/movie-seat-pr/app/Http/Middleware/Authenticate.php"
>
  <violation
    line="15"
    source="PrivateNoUnderscore"
    severity="High"
    type="checkstyle"
    message="Protected member variable &quot;auth&quot; must contain a leading underscore"
    severity-level="0"
    popup-message="Protected member variable &quot;auth&quot; must contain a leading underscore"
  />
  <line number='6'>use Illuminate\Contracts\Auth\Guard;</line>
  <line number='7'></line>
  <line number='8'>class Authenticate</line>
  <line number='9'>{</line>
  <line number='10'>    /**</line>
  <line number='11'>     * The Guard implementation.</line>
  <line number='12'>     *</line>
  <line number='13'>     * @var Guard</line>
  <line number='14'>     */</line>
  <line number='15'>    protected $auth;</line>
  <line number='16'></line>
  <line number='17'>    /**</line>
  <line number='18'>     * Create a new middleware instance.</line>
  <line number='19'>     *</line>
  <line number='20'>     * @param  Guard  $auth</line>
  <line number='21'>     * @return void</line>
  <line number='22'>     */</line>
  <line number='23'>    public function __construct(Guard $auth)</line>
  <line number='24'>    {</line>
  <line number='25'>        $this-&gt;auth = $auth;</line>
  <type type='checkstyle' number='1' suppressed='0'/>
</file>
