<?xml version="1.0" encoding="UTF-8"?>
<file
  name="database/migrations/2014_10_12_100000_create_password_resets_table.php"
  last-modified="1474359102000"
  file="/var/jenkins_home/workspace/movie-seat-pr/database/migrations/2014_10_12_100000_create_password_resets_table.php"
>
  <violation
    line="15"
    source="ContentAfterOpenBracket"
    severity="High"
    type="checkstyle"
    message="Opening parenthesis of a multi-line function call must be the last content on the line"
    severity-level="0"
    popup-message="Opening parenthesis of a multi-line function call must be the last content on the line"
  />
  <violation
    line="19"
    source="CloseBracketLine"
    severity="High"
    type="checkstyle"
    message="Closing parenthesis of a multi-line function call must be on a line by itself"
    severity-level="0"
    popup-message="Closing parenthesis of a multi-line function call must be on a line by itself"
  />
  <line number='6'>class CreatePasswordResetsTable extends Migration</line>
  <line number='7'>{</line>
  <line number='8'>    /**</line>
  <line number='9'>     * Run the migrations.</line>
  <line number='10'>     *</line>
  <line number='11'>     * @return void</line>
  <line number='12'>     */</line>
  <line number='13'>    public function up()</line>
  <line number='14'>    {</line>
  <line number='15'>        Schema::create('password_resets', function (Blueprint $table) {</line>
  <line number='16'>            $table-&gt;string('email')-&gt;index();</line>
  <line number='17'>            $table-&gt;string('token')-&gt;index();</line>
  <line number='18'>            $table-&gt;timestamp('created_at');</line>
  <line number='19'>        });</line>
  <line number='20'>    }</line>
  <line number='21'></line>
  <line number='22'>    /**</line>
  <line number='23'>     * Reverse the migrations.</line>
  <line number='24'>     *</line>
  <line number='25'>     * @return void</line>
  <line number='26'>     */</line>
  <line number='27'>    public function down()</line>
  <line number='28'>    {</line>
  <line number='29'>        Schema::drop('password_resets');</line>
  <type type='checkstyle' number='2' suppressed='0'/>
</file>
